neural_shell-1.3.5.dist-info/licenses/LICENSE
nlsh/__init__.py
nlsh/backends.py
nlsh/cli.py
nlsh/config.py
nlsh/editor.py
nlsh/git_commit.py
nlsh/image_utils.py
nlsh/main.py
nlsh/prompt.py
nlsh/spinner.py
nlsh/token_count.py
nlsh/tools/__init__.py
nlsh/tools/base.py
nlsh/tools/directory.py
nlsh/tools/environment.py
nlsh/tools/system.py
neural_shell-1.3.5.dist-info/METADATA
neural_shell-1.3.5.dist-info/WHEEL
neural_shell-1.3.5.dist-info/entry_points.txt
neural_shell-1.3.5.dist-info/top_level.txt
neural_shell-1.3.5.dist-info/RECORD
