Metadata-Version: 2.4
Name: neural-shell
Version: 1.3.5
Summary: Neural Shell (nlsh) - AI-driven command-line assistant
Home-page: https://github.com/eqld/nlsh
Author: eqld
Author-email: eqld <44535024+eqld@users.noreply.github.com>
License: MIT
Classifier: Programming Language :: Python :: 3
Classifier: License :: OSI Approved :: MIT License
Classifier: Operating System :: OS Independent
Classifier: Topic :: Utilities
Classifier: Environment :: Console
Requires-Python: >=3.8
License-File: LICENSE
Requires-Dist: openai>=1.0.0
Requires-Dist: pyyaml>=5.1
Requires-Dist: tiktoken>=0.5.0
Requires-Dist: pillow>=8.0.0
Dynamic: author
Dynamic: home-page
Dynamic: license-file
Dynamic: requires-python
